truckman/__init__.py
truckman/load.py
truckman/save.py
truckman-0.0.1.dist-info/LICENSE.txt
truckman-0.0.1.dist-info/METADATA
truckman-0.0.1.dist-info/WHEEL
truckman-0.0.1.dist-info/entry_points.txt
truckman-0.0.1.dist-info/top_level.txt
truckman-0.0.1.dist-info/RECORD
