Metadata-Version: 2.1
Name: truckman
Version: 0.0.1
Summary: Save and load Docker named volumes.
Home-page: https://github.com/Tsuribori/truckman
Author: Tsuribori
Author-email: tsuribori@tutanota.com
License: UNKNOWN
Keywords: docker volume save load backup transfer
Platform: UNKNOWN
Classifier: Programming Language :: Python :: 3
Classifier: Development Status :: 3 - Alpha
Classifier: Environment :: Console
Classifier: Intended Audience :: Developers
Classifier: Intended Audience :: System Administrators
Classifier: Operating System :: POSIX :: Linux
Classifier: Topic :: System :: Archiving :: Backup
Classifier: Topic :: System :: Archiving
Requires-Python: >=3.5
Requires-Dist: docker
